{"State.c57b6e05-533e-4be9-b410-2f1e0353ff7f": {"id": "c57b6e05-533e-4be9-b410-2f1e0353ff7f", "created_at": "2022-03-03T16:54:35.360909", "updated_at": "2022-03-03T16:54:35.360921", "name": "California", "__class__": "State"}, "State.60a518c6-f0fa-4ab4-8e72-bfa95794145c": {"id": "60a518c6-f0fa-4ab4-8e72-bfa95794145c", "created_at": "2022-03-03T16:54:35.361787", "updated_at": "2022-03-03T16:54:35.361790", "name": "Arizona", "__class__": "State"}, "Place.6cf74118-8568-4cb7-8c36-b90487a2cc2c": {"id": "6cf74118-8568-4cb7-8c36-b90487a2cc2c", "created_at": "2022-03-03T16:54:35.362771", "updated_at": "2022-03-03T16:54:35.362775", "city_id": "0001", "user_id": "0001", "name": "My little house", "number_rooms": 4, "number_bathrooms": 2, "max_guest": 10, "price_by_night": 300, "latitude": 37.773972, "longitude": -122.431297, "__class__": "Place"}, "State.3c946ea8-9fd5-4399-9243-e6101564202b": {"id": "3c946ea8-9fd5-4399-9243-e6101564202b", "created_at": "2022-03-03T17:02:02.665788", "updated_at": "2022-03-03T17:02:02.665922", "name=\"California\"": "a", "__class__": "State"}, "State.4f5979f8-7cec-4171-8d8d-be1608942070": {"id": "4f5979f8-7cec-4171-8d8d-be1608942070", "created_at": "2022-03-03T17:02:02.667003", "updated_at": "2022-03-03T17:02:02.667054", "name=\"Arizona\"": "a", "__class__": "State"}, "Place.0bdbf644-2ecb-49f3-a1b8-95febb7fcdc7": {"id": "0bdbf644-2ecb-49f3-a1b8-95febb7fcdc7", "created_at": "2022-03-03T17:02:02.669677", "updated_at": "2022-03-03T17:02:02.669726", "city_id=\"0001\"": "user_id=\"0001\"", "name=\"My_little_house\"": "number_rooms=4", "number_bathrooms=2": "max_guest=10", "price_by_night=300": "latitude=37.773972", "longitude=-122.431297": "o", "__class__": "Place"}, "State.ad07b791-d7dc-4347-8f38-4235a18cc118": {"id": "ad07b791-d7dc-4347-8f38-4235a18cc118", "created_at": "2022-03-03T18:10:11.119483", "updated_at": "2022-03-03T18:10:11.119642", "name": "California", "__class__": "State"}, "State.1a9fd6aa-5be8-4a81-8f73-93bea04e3a5e": {"id": "1a9fd6aa-5be8-4a81-8f73-93bea04e3a5e", "created_at": "2022-03-03T18:10:11.120661", "updated_at": "2022-03-03T18:10:11.120755", "name": "Arizona", "__class__": "State"}, "Place.b1d09350-2ac4-4331-9768-099561c2b89b": {"id": "b1d09350-2ac4-4331-9768-099561c2b89b", "created_at": "2022-03-03T18:10:11.130150", "updated_at": "2022-03-03T18:10:11.130278", "city_id": "0001", "user_id": "0001", "name": "My little house", "number_rooms": "4", "number_bathrooms": "2", "max_guest": "10", "price_by_night": "300", "latitude": "37.773972", "longitude": "-122.431297", "__class__": "Place"}, "State.d1a63289-e9c6-447c-a6d4-8703a299ae51": {"id": "d1a63289-e9c6-447c-a6d4-8703a299ae51", "created_at": "2022-03-03T18:12:48.061485", "updated_at": "2022-03-03T18:12:48.061624", "name": "California", "__class__": "State"}, "State.b9a99ca8-de42-48f4-b783-aecee9ebbf2f": {"id": "b9a99ca8-de42-48f4-b783-aecee9ebbf2f", "created_at": "2022-03-03T18:12:48.067974", "updated_at": "2022-03-03T18:12:48.068970", "name": "Arizona", "__class__": "State"}, "Place.6a8c622c-39ee-4a1d-b1ed-6c3efd00051b": {"id": "6a8c622c-39ee-4a1d-b1ed-6c3efd00051b", "created_at": "2022-03-03T18:12:48.070937", "updated_at": "2022-03-03T18:12:48.071050", "city_id": "0001", "user_id": "0001", "name": "My little house", "number_rooms": "4", "number_bathrooms": "2", "max_guest": "10", "price_by_night": "300", "latitude": "37.773972", "longitude": "-122.431297", "__class__": "Place"}, "State.9c4f80aa-e215-4c9b-9c91-9a4ae6b2163f": {"id": "9c4f80aa-e215-4c9b-9c91-9a4ae6b2163f", "created_at": "2022-03-03T18:13:33.180004", "updated_at": "2022-03-03T18:13:33.180699", "name": "California", "__class__": "State"}, "State.d3bebd10-9809-497b-bc01-0d173d95bfd7": {"id": "d3bebd10-9809-497b-bc01-0d173d95bfd7", "created_at": "2022-03-03T18:13:33.185533", "updated_at": "2022-03-03T18:13:33.185610", "name": "Arizona", "__class__": "State"}, "Place.0dd0b646-ea83-4b08-863e-d18a38e577a8": {"id": "0dd0b646-ea83-4b08-863e-d18a38e577a8", "created_at": "2022-03-03T18:13:33.188467", "updated_at": "2022-03-03T18:13:33.188613", "city_id": "0001", "user_id": "0001", "name": "My little house", "number_rooms": "4", "number_bathrooms": "2", "max_guest": "10", "price_by_night": "300", "latitude": "37.773972", "longitude": "-122.431297", "__class__": "Place"}, "State.32217837-8839-446a-8a09-f11ed3028982": {"id": "32217837-8839-446a-8a09-f11ed3028982", "created_at": 